sempubflow/__init__.py
sempubflow/event_info.py
sempubflow/homepage.py
sempubflow/jsoncache.py
sempubflow/llm.py
sempubflow/orcid_auth.py
sempubflow/sempubflow_cmd.py
sempubflow/version.py
sempubflow/webserver.py
sempubflow/elements/__init__.py
sempubflow/elements/drag_and_drop.py
sempubflow/elements/proceedings_form.py
sempubflow/elements/scholar_form.py
sempubflow/elements/suggestion.py
sempubflow/models/__init__.py
sempubflow/models/affiliation.py
sempubflow/models/proceedings.py
sempubflow/models/scholar.py
sempubflow/models/templates/__init__.py
sempubflow/models/templates/ceurws.py
sempubflow/services/__init__.py
sempubflow/services/dblp.py
sempubflow/services/wikidata.py
sempubflow-0.0.3.dist-info/METADATA
sempubflow-0.0.3.dist-info/WHEEL
sempubflow-0.0.3.dist-info/entry_points.txt
sempubflow-0.0.3.dist-info/licenses/LICENSE
sempubflow-0.0.3.dist-info/RECORD
