Metadata-Version: 2.1
Name: SemPubFlow
Version: 0.0.3
Summary: Semantic Publishing Workflow support
Project-URL: Home, https://github.com/WolfgangFahl/SemPubFlow
Project-URL: Documentation, https://wiki.bitplan.com/index.php/SemPubFlow
Project-URL: Source, https://github.com/WolfgangFahl/SemPubFlow
Author-email: Wolfgang Fahl <wf@bitplan.com>
Maintainer-email: Wolfgang Fahl <wf@bitplan.com>
License-Expression: Apache-2.0
License-File: LICENSE
Keywords: CEUR-WS,nicegui,publishing,scholars
Classifier: Development Status :: 4 - Beta
Classifier: Environment :: Web Environment
Classifier: Intended Audience :: Developers
Classifier: Intended Audience :: Education
Classifier: Intended Audience :: Science/Research
Classifier: License :: OSI Approved :: Apache Software License
Classifier: Operating System :: OS Independent
Classifier: Programming Language :: Python :: 3 :: Only
Classifier: Programming Language :: Python :: 3.9
Classifier: Programming Language :: Python :: 3.10
Classifier: Programming Language :: Python :: 3.11
Classifier: Topic :: Software Development :: Libraries :: Python Modules
Requires-Python: >=3.9
Requires-Dist: bcrypt
Requires-Dist: beautifulsoup4>=4.12.2
Requires-Dist: ngwidgets>=0.6.0
Requires-Dist: nicegui>=1.3.13
Requires-Dist: oauthlib
Requires-Dist: openai
Requires-Dist: orjson
Requires-Dist: pygments
Requires-Dist: pylodstorage
Requires-Dist: requests-oauthlib
Provides-Extra: test
Requires-Dist: green; extra == 'test'
